Metadata-Version: 1.0
Name: nose-machineout
Version: 0.2
Summary: 
